README.rst
setup.py
jsonobject/__init__.py
jsonobject/attributes.py
jsonobject/utils.py
python_jsonobject.egg-info/PKG-INFO
python_jsonobject.egg-info/SOURCES.txt
python_jsonobject.egg-info/dependency_links.txt
python_jsonobject.egg-info/not-zip-safe
python_jsonobject.egg-info/top_level.txt